Workbook

Sheet Dashboard
A1: POLYMARKET PORTFOLIO DASHBOARD
A3: PORTFOLIO SUMMARY
A4: Metric | B4: Value | C4: Limit | D4: Status
A5: Total Bankroll | B5: 10000
A6: Deployed Capital | B6: =Positions!L2 -> 210 | C6: =B5*0.9 -> 9000 | D6: =IF(B6>C6,"⚠ BREACH","✓ OK") -> ✓ OK
A7: Cash Reserve | B7: =B5-B6 -> 9790 | C7: =B5*0.1 -> 1000 | D7: =IF(B7<C7,"⚠ LOW","✓ OK") -> ✓ OK
A8: Open Positions | B8: =COUNTA(Positions!A3:A102)-COUNTBLANK(Positions!A3:A102) -> -98 | C8: 20 | D8: =IF(B8>C8,"⚠ BREACH","✓ OK") -> ✓ OK
A9: Max Single Position % | B9: =MAX(Positions!K3:K102) -> 210 | C9: 0.1 | D9: =IF(B9>C9,"⚠ BREACH","✓ OK") -> ⚠ BREACH
A10: Max Cluster Exposure % | B10: =MAX(Correlations!H3:H12) -> 0.084 | C10: 0.25 | D10: =IF(B10>C10,"⚠ BREACH","✓ OK") -> ✓ OK
A11: Current Drawdown % | B11: =-MIN(0,(B5-Attribution!G2)/Attribution!G2) -> 0.0049751244 | C11: 0.15 | D11: =IF(B11>C11,"⚠ BREACH","✓ OK") -> ✓ OK
A12: Win Rate (Last 20) | B12: =Attribution!J2 -> 1
A13: Avg Edge Captured | B13: =Attribution!K2 -> 0.15
A14: Portfolio Brier Score | B14: =Attribution!L2 -> 0.16
A17: RISK ALERTS | F17: QUICK SIZING CALCULATOR
A18: Positions Approaching Resolution (< 7 days) | F18: Your Probability: | G18: 0.65
A19: =COUNTIF(Positions!H3:H102,"<"&TODAY()+7) -> 1 | F19: Market Probability: | G19: 0.55
A20: Positions with Edge Decay (current edge < 50% of entry edge) | F20: Edge: | G20: =G18-G19 -> 0.1
A21: =SUMPRODUCT((Positions!F3:F102<Positions!E3:E102*0.5)*1) -> 1 | F21: Kelly Fraction: | G21: 0.25
A22: Highly Correlated New Positions Warning | F22: Suggested Size ($): | G22: =IF(ABS(G20)<0.05,0,MAX(0,B5*G21*((G18*(1-G19)/G19)-(1-G18))/((1-G19)/G19))) -> 555.55556
A23: Check Correlations tab before adding to: | F23: As % of Bankroll: | G23: =IF(B5>0,G22/B5,0) -> 0.055555556
A24: =IF(Correlations!H3>0.2,Correlations!A3,"") -> Cluster Name | F24: Position Limit Check: | G24: =IF(G23>0.1,"⚠ EXCEEDS 10% LIMIT",IF(G22>0,"✓ OK","NO BET")) -> ✓ OK

Sheet Positions
A1: CURRENT POSITIONS
A2: Market ID | B2: Market Name | C2: Direction | D2: Entry Date | E2: Entry Edge | F2: Current Edge | G2: Entry Price | H2: Current Price | I2: Resolution Date | J2: Shares | K2: Total: | L2: =SUM(K3:K102) -> 210 | M2: =SUM(M3:M102) -> 15 | N2: P&L % | O2: Theta ($/day) | P2: Vega (sensitivity) | Q2: Cluster | R2: Confidence | S2: Notes
A3: trump-2028 | B3: Trump wins 2028 election | C3: YES | D3: 45672 | E3: 0.08 | F3: =G3-H3 -> -0.03 | G3: 0.42 | H3: 0.45 | I3: 47062 | J3: 500 | K3: =J3*G3 -> 210 | L3: =K3/Dashboard!$B$5 -> 0.021 | M3: =J3*(H3-G3) -> 15 | N3: =IF(K3>0,M3/K3,0) -> 0.071428571 | O3: =IF(I3>TODAY(),(K3*0.02)/(I3-TODAY()),0) -> 0.0041461007 | P3: =K3*0.5 -> 105 | Q3: US Politics | R3: High
F4: =G4-H4 -> 0 | K4: =J4*G4 -> 0 | L4: =K4/Dashboard!$B$5 -> 0 | M4: =J4*(H4-G4) -> 0 | N4: =IF(K4>0,M4/K4,0) -> 0 | O4: =IF(I4>TODAY(),(K4*0.02)/(I4-TODAY()),0) -> 0 | P4: =K4*0.5 -> 0
F5: =G5-H5 -> 0 | K5: =J5*G5 -> 0 | L5: =K5/Dashboard!$B$5 -> 0 | M5: =J5*(H5-G5) -> 0 | N5: =IF(K5>0,M5/K5,0) -> 0 | O5: =IF(I5>TODAY(),(K5*0.02)/(I5-TODAY()),0) -> 0 | P5: =K5*0.5 -> 0
F6: =G6-H6 -> 0 | K6: =J6*G6 -> 0 | L6: =K6/Dashboard!$B$5 -> 0 | M6: =J6*(H6-G6) -> 0 | N6: =IF(K6>0,M6/K6,0) -> 0 | O6: =IF(I6>TODAY(),(K6*0.02)/(I6-TODAY()),0) -> 0 | P6: =K6*0.5 -> 0
F7: =G7-H7 -> 0 | K7: =J7*G7 -> 0 | L7: =K7/Dashboard!$B$5 -> 0 | M7: =J7*(H7-G7) -> 0 | N7: =IF(K7>0,M7/K7,0) -> 0 | O7: =IF(I7>TODAY(),(K7*0.02)/(I7-TODAY()),0) -> 0 | P7: =K7*0.5 -> 0
F8: =G8-H8 -> 0 | K8: =J8*G8 -> 0 | L8: =K8/Dashboard!$B$5 -> 0 | M8: =J8*(H8-G8) -> 0 | N8: =IF(K8>0,M8/K8,0) -> 0 | O8: =IF(I8>TODAY(),(K8*0.02)/(I8-TODAY()),0) -> 0 | P8: =K8*0.5 -> 0
F9: =G9-H9 -> 0 | K9: =J9*G9 -> 0 | L9: =K9/Dashboard!$B$5 -> 0 | M9: =J9*(H9-G9) -> 0 | N9: =IF(K9>0,M9/K9,0) -> 0 | O9: =IF(I9>TODAY(),(K9*0.02)/(I9-TODAY()),0) -> 0 | P9: =K9*0.5 -> 0
F10: =G10-H10 -> 0 | K10: =J10*G10 -> 0 | L10: =K10/Dashboard!$B$5 -> 0 | M10: =J10*(H10-G10) -> 0 | N10: =IF(K10>0,M10/K10,0) -> 0 | O10: =IF(I10>TODAY(),(K10*0.02)/(I10-TODAY()),0) -> 0 | P10: =K10*0.5 -> 0
F11: =G11-H11 -> 0 | K11: =J11*G11 -> 0 | L11: =K11/Dashboard!$B$5 -> 0 | M11: =J11*(H11-G11) -> 0 | N11: =IF(K11>0,M11/K11,0) -> 0 | O11: =IF(I11>TODAY(),(K11*0.02)/(I11-TODAY()),0) -> 0 | P11: =K11*0.5 -> 0
F12: =G12-H12 -> 0 | K12: =J12*G12 -> 0 | L12: =K12/Dashboard!$B$5 -> 0 | M12: =J12*(H12-G12) -> 0 | N12: =IF(K12>0,M12/K12,0) -> 0 | O12: =IF(I12>TODAY(),(K12*0.02)/(I12-TODAY()),0) -> 0 | P12: =K12*0.5 -> 0
F13: =G13-H13 -> 0 | K13: =J13*G13 -> 0 | L13: =K13/Dashboard!$B$5 -> 0 | M13: =J13*(H13-G13) -> 0 | N13: =IF(K13>0,M13/K13,0) -> 0 | O13: =IF(I13>TODAY(),(K13*0.02)/(I13-TODAY()),0) -> 0 | P13: =K13*0.5 -> 0

Sheet Sizing
A1: POSITION SIZING CALCULATOR
A3: PARAMETERS | D3: NEW POSITION CALCULATOR
A4: Bankroll | B4: =Dashboard!B5 -> 10000 | D4: Market Name | E4: Example Market
A5: Kelly Fraction | B5: 0.25 | D5: Your Probability | E5: 0.65
A6: Max Position % | B6: 0.1 | D6: Market Price | E6: 0.55
A7: Min Edge Threshold | B7: 0.05 | D7: Confidence Level | E7: High
A8: Confidence Multiplier - High | B8: 1 | D8: Available Liquidity ($) | E8: 50000
A9: Confidence Multiplier - Medium | B9: 0.7 | D9: Days to Resolution | E9: 90
A10: Confidence Multiplier - Low | B10: 0.4
A11: Confidence Multiplier - Speculative | B11: 0.2 | D11: CALCULATED OUTPUTS
D12: Edge | E12: =E5-E6 -> 0.1
D13: Bet Direction | E13: =IF(E5>E6,"YES","NO") -> YES
D14: Odds (b) | E14: =IF(E6>0,IF(E5>E6,(1-E6)/E6,E6/(1-E6)),1) -> 0.81818182
D15: Raw Kelly % | E15: =IF(ABS(E12)<$B$7,0,IF(E14>0,MAX(0,(E5*E14-(1-E5))/E14),0)) -> 0.22222222
D16: Fractional Kelly % | E16: =E15*$B$5 -> 0.055555556
D17: Confidence Adjusted % | E17: =E16*IF(E7="High",$B$8,IF(E7="Medium",$B$9,IF(E7="Low",$B$10,$B$11))) -> 0.055555556
D18: Position Limit Check | E18: =MIN(E17,$B$6) -> 0.055555556
D19: Liquidity Adjusted | E19: =IF($B$4>0,MIN(E18,E8*0.1/$B$4),E18) -> 0.055555556
D20: Final Position Size ($) | E20: =E19*$B$4 -> 555.55556
D21: Final Position % | E21: =E19 -> 0.055555556
D22: Expected Value ($) | E22: =IF(E6>0,E20*(E5*(1-E6)/E6-(1-E5)),0) -> 101.0101
D23: Max Loss ($) | E23: =E20 -> 555.55556
D24: Max Gain ($) | E24: =IF(E6>0,E20*(1-E6)/E6,0) -> 454.54545
D26: RECOMMENDATION
D27: =IF(ABS(E12)<$B$7,"NO BET - Edge below threshold",IF(E20>0,CONCATENATE("BET ",E13," with $",ROUND(E20,0)," (",ROUND(E21*100,1),"% of bankroll)"),"NO BET")) -> BET YES with $556 (5.6% of bankroll)

Sheet Greeks
A1: PORTFOLIO GREEKS & SENSITIVITIES
A3: Greek Definitions for Prediction Markets:
A4: Theta: Daily time decay of edge value (edge erodes as resolution approaches)
A5: Vega: Sensitivity to probability volatility (news impact)
A6: Delta: Position directional exposure ($1 move per 1% prob change)
A7: Gamma: Rate of delta change as resolution approaches
A9: PORTFOLIO GREEKS SUMMARY
A10: Greek | B10: Portfolio Total | C10: Daily Impact ($) | D10: Weekly Impact ($)
A11: Theta (Time Decay) | B11: =SUM(Positions!O3:O102) -> 0.0041461007 | C11: =-B11 -> -0.0041461007 | D11: =-B11*7 -> -0.029022705
A12: Vega (Vol Sensitivity) | B12: =SUM(Positions!P3:P102) -> 105 | C12: =B12*0.01 -> 1.05 | D12: =B12*0.05 -> 5.25
A13: Delta (Directional) | B13: =SUMPRODUCT((Positions!C3:C102="YES")*Positions!K3:K102)-SUMPRODUCT((Positions!C3:C102="NO")*Positions!K3:K102) -> 210
A14: Net Exposure | B14: =ABS(B13) -> 210
A17: PER-POSITION GREEKS
A18: Market | B18: Days to Res | C18: Position $ | D18: Theta | E18: Vega | F18: Delta | G18: Edge Decay Rate
A19: =Positions!B3 -> Trump wins 2028 election | B19: =IF(Positions!I3>0,Positions!I3-TODAY(),"") -> 1013 | C19: =Positions!K3 -> 210 | D19: =Positions!O3 -> 0.0041461007 | E19: =Positions!P3 -> 105 | F19: =IF(Positions!C3="YES",Positions!K3,-Positions!K3) -> 210 | G19: =IF(AND(Positions!E3>0,B19>0),(Positions!E3-Positions!F3)/Positions!E3,"") -> 1.375
A20: =Positions!B4 -> 0 | B20: =IF(Positions!I4>0,Positions!I4-TODAY(),"") | C20: =Positions!K4 -> 0 | D20: =Positions!O4 -> 0 | E20: =Positions!P4 -> 0 | F20: =IF(Positions!C4="YES",Positions!K4,-Positions!K4) -> 0 | G20: =IF(AND(Positions!E4>0,B20>0),(Positions!E4-Positions!F4)/Positions!E4,"")
A21: =Positions!B5 -> 0 | B21: =IF(Positions!I5>0,Positions!I5-TODAY(),"") | C21: =Positions!K5 -> 0 | D21: =Positions!O5 -> 0 | E21: =Positions!P5 -> 0 | F21: =IF(Positions!C5="YES",Positions!K5,-Positions!K5) -> 0 | G21: =IF(AND(Positions!E5>0,B21>0),(Positions!E5-Positions!F5)/Positions!E5,"")
A22: =Positions!B6 -> 0 | B22: =IF(Positions!I6>0,Positions!I6-TODAY(),"") | C22: =Positions!K6 -> 0 | D22: =Positions!O6 -> 0 | E22: =Positions!P6 -> 0 | F22: =IF(Positions!C6="YES",Positions!K6,-Positions!K6) -> 0 | G22: =IF(AND(Positions!E6>0,B22>0),(Positions!E6-Positions!F6)/Positions!E6,"")
A23: =Positions!B7 -> 0 | B23: =IF(Positions!I7>0,Positions!I7-TODAY(),"") | C23: =Positions!K7 -> 0 | D23: =Positions!O7 -> 0 | E23: =Positions!P7 -> 0 | F23: =IF(Positions!C7="YES",Positions!K7,-Positions!K7) -> 0 | G23: =IF(AND(Positions!E7>0,B23>0),(Positions!E7-Positions!F7)/Positions!E7,"")
A24: =Positions!B8 -> 0 | B24: =IF(Positions!I8>0,Positions!I8-TODAY(),"") | C24: =Positions!K8 -> 0 | D24: =Positions!O8 -> 0 | E24: =Positions!P8 -> 0 | F24: =IF(Positions!C8="YES",Positions!K8,-Positions!K8) -> 0 | G24: =IF(AND(Positions!E8>0,B24>0),(Positions!E8-Positions!F8)/Positions!E8,"")
A25: =Positions!B9 -> 0 | B25: =IF(Positions!I9>0,Positions!I9-TODAY(),"") | C25: =Positions!K9 -> 0 | D25: =Positions!O9 -> 0 | E25: =Positions!P9 -> 0 | F25: =IF(Positions!C9="YES",Positions!K9,-Positions!K9) -> 0 | G25: =IF(AND(Positions!E9>0,B25>0),(Positions!E9-Positions!F9)/Positions!E9,"")
A26: =Positions!B10 -> 0 | B26: =IF(Positions!I10>0,Positions!I10-TODAY(),"") | C26: =Positions!K10 -> 0 | D26: =Positions!O10 -> 0 | E26: =Positions!P10 -> 0 | F26: =IF(Positions!C10="YES",Positions!K10,-Positions!K10) -> 0 | G26: =IF(AND(Positions!E10>0,B26>0),(Positions!E10-Positions!F10)/Positions!E10,"")
A27: =Positions!B11 -> 0 | B27: =IF(Positions!I11>0,Positions!I11-TODAY(),"") | C27: =Positions!K11 -> 0 | D27: =Positions!O11 -> 0 | E27: =Positions!P11 -> 0 | F27: =IF(Positions!C11="YES",Positions!K11,-Positions!K11) -> 0 | G27: =IF(AND(Positions!E11>0,B27>0),(Positions!E11-Positions!F11)/Positions!E11,"")
A28: =Positions!B12 -> 0 | B28: =IF(Positions!I12>0,Positions!I12-TODAY(),"") | C28: =Positions!K12 -> 0 | D28: =Positions!O12 -> 0 | E28: =Positions!P12 -> 0 | F28: =IF(Positions!C12="YES",Positions!K12,-Positions!K12) -> 0 | G28: =IF(AND(Positions!E12>0,B28>0),(Positions!E12-Positions!F12)/Positions!E12,"")

Sheet Correlations
A1: CORRELATION CLUSTERS & EXPOSURE
A3: Cluster Name | B3: Description | C3: # Positions | D3: Total Exposure ($) | E3: Exposure % | F3: Limit % | G3: Status | H3: Utilization
A4: US Politics | B4: US elections, policy, politicians | C4: =COUNTIF(Positions!Q:Q,A4) -> 1 | D4: =SUMIF(Positions!Q:Q,A4,Positions!K:K) -> 210 | E4: =IF(Dashboard!$B$5>0,D4/Dashboard!$B$5,0) -> 0.021 | F4: 0.25 | G4: =IF(E4>F4,"⚠ BREACH","✓ OK") -> ✓ OK | H4: =IF(F4>0,E4/F4,0) -> 0.084
A5: Crypto | B5: Bitcoin, Ethereum, crypto regulation | C5: =COUNTIF(Positions!Q:Q,A5) -> 0 | D5: =SUMIF(Positions!Q:Q,A5,Positions!K:K) -> 0 | E5: =IF(Dashboard!$B$5>0,D5/Dashboard!$B$5,0) -> 0 | F5: 0.2 | G5: =IF(E5>F5,"⚠ BREACH","✓ OK") -> ✓ OK | H5: =IF(F5>0,E5/F5,0) -> 0
A6: Fed/Macro | B6: Interest rates, Fed decisions, inflation | C6: =COUNTIF(Positions!Q:Q,A6) -> 0 | D6: =SUMIF(Positions!Q:Q,A6,Positions!K:K) -> 0 | E6: =IF(Dashboard!$B$5>0,D6/Dashboard!$B$5,0) -> 0 | F6: 0.2 | G6: =IF(E6>F6,"⚠ BREACH","✓ OK") -> ✓ OK | H6: =IF(F6>0,E6/F6,0) -> 0
A7: Tech | B7: Tech companies, AI, product launches | C7: =COUNTIF(Positions!Q:Q,A7) -> 0 | D7: =SUMIF(Positions!Q:Q,A7,Positions!K:K) -> 0 | E7: =IF(Dashboard!$B$5>0,D7/Dashboard!$B$5,0) -> 0 | F7: 0.15 | G7: =IF(E7>F7,"⚠ BREACH","✓ OK") -> ✓ OK | H7: =IF(F7>0,E7/F7,0) -> 0
A8: Sports | B8: Sports outcomes, championships | C8: =COUNTIF(Positions!Q:Q,A8) -> 0 | D8: =SUMIF(Positions!Q:Q,A8,Positions!K:K) -> 0 | E8: =IF(Dashboard!$B$5>0,D8/Dashboard!$B$5,0) -> 0 | F8: 0.15 | G8: =IF(E8>F8,"⚠ BREACH","✓ OK") -> ✓ OK | H8: =IF(F8>0,E8/F8,0) -> 0
A9: Entertainment | B9: Awards, media, celebrities | C9: =COUNTIF(Positions!Q:Q,A9) -> 0 | D9: =SUMIF(Positions!Q:Q,A9,Positions!K:K) -> 0 | E9: =IF(Dashboard!$B$5>0,D9/Dashboard!$B$5,0) -> 0 | F9: 0.1 | G9: =IF(E9>F9,"⚠ BREACH","✓ OK") -> ✓ OK | H9: =IF(F9>0,E9/F9,0) -> 0
A10: International | B10: Non-US politics and events | C10: =COUNTIF(Positions!Q:Q,A10) -> 0 | D10: =SUMIF(Positions!Q:Q,A10,Positions!K:K) -> 0 | E10: =IF(Dashboard!$B$5>0,D10/Dashboard!$B$5,0) -> 0 | F10: 0.15 | G10: =IF(E10>F10,"⚠ BREACH","✓ OK") -> ✓ OK | H10: =IF(F10>0,E10/F10,0) -> 0
A11: Legal/Court | B11: Court cases, legal outcomes | C11: =COUNTIF(Positions!Q:Q,A11) -> 0 | D11: =SUMIF(Positions!Q:Q,A11,Positions!K:K) -> 0 | E11: =IF(Dashboard!$B$5>0,D11/Dashboard!$B$5,0) -> 0 | F11: 0.1 | G11: =IF(E11>F11,"⚠ BREACH","✓ OK") -> ✓ OK | H11: =IF(F11>0,E11/F11,0) -> 0
A12: Science | B12: Scientific discoveries, space | C12: =COUNTIF(Positions!Q:Q,A12) -> 0 | D12: =SUMIF(Positions!Q:Q,A12,Positions!K:K) -> 0 | E12: =IF(Dashboard!$B$5>0,D12/Dashboard!$B$5,0) -> 0 | F12: 0.1 | G12: =IF(E12>F12,"⚠ BREACH","✓ OK") -> ✓ OK | H12: =IF(F12>0,E12/F12,0) -> 0
A13: Other | B13: Miscellaneous | C13: =COUNTIF(Positions!Q:Q,A13) -> 0 | D13: =SUMIF(Positions!Q:Q,A13,Positions!K:K) -> 0 | E13: =IF(Dashboard!$B$5>0,D13/Dashboard!$B$5,0) -> 0 | F13: 0.1 | G13: =IF(E13>F13,"⚠ BREACH","✓ OK") -> ✓ OK | H13: =IF(F13>0,E13/F13,0) -> 0
A16: POSITION CORRELATION NOTES
A17: Use this section to note specific correlations between positions
A18: Position 1 | B18: Position 2 | C18: Correlation Type | D18: Direction | E18: Notes

Sheet Risk Limits
A1: RISK LIMITS MONITORING
A3: POSITION LIMITS
A4: Limit Type | B4: Limit Value | C4: Current Value | D4: Utilization | E4: Status | F4: Action Required
A5: Max Single Position % | B5: 0.1 | C5: =MAX(Positions!L3:L102) -> 0.021 | D5: =IF(B5>0,C5/B5,0) -> 0.21 | E5: =IF(D5>1,"⚠ BREACH",IF(D5>0.8,"⚡ WARNING","✓ OK")) -> ✓ OK | F5: =IF(D5>1,"REDUCE IMMEDIATELY",IF(D5>0.8,"Monitor closely",""))
A6: Max Cluster Exposure % | B6: 0.25 | C6: =MAX(Correlations!E4:E13) -> 0.021 | D6: =IF(B6>0,C6/B6,0) -> 0.084 | E6: =IF(D6>1,"⚠ BREACH",IF(D6>0.8,"⚡ WARNING","✓ OK")) -> ✓ OK | F6: =IF(D6>1,"REDUCE IMMEDIATELY",IF(D6>0.8,"Monitor closely",""))
A7: Max Total Deployed % | B7: 0.9 | C7: =Dashboard!B6/Dashboard!B5 -> 0.021 | D7: =IF(B7>0,C7/B7,0) -> 0.023333333 | E7: =IF(D7>1,"⚠ BREACH",IF(D7>0.8,"⚡ WARNING","✓ OK")) -> ✓ OK | F7: =IF(D7>1,"REDUCE IMMEDIATELY",IF(D7>0.8,"Monitor closely",""))
A8: Min Cash Reserve % | B8: 0.1 | C8: =Dashboard!B7/Dashboard!B5 -> 0.979 | D8: =IF(B8>0,C8/B8,0) -> 9.79 | E8: =IF(D8>1,"⚠ BREACH",IF(D8>0.8,"⚡ WARNING","✓ OK")) -> ⚠ BREACH | F8: =IF(D8>1,"REDUCE IMMEDIATELY",IF(D8>0.8,"Monitor closely","")) -> REDUCE IMMEDIATELY
A9: Max Positions Count | B9: 20 | C9: =Dashboard!B8 -> -98 | D9: =IF(B9>0,C9/B9,0) -> -4.9 | E9: =IF(D9>1,"⚠ BREACH",IF(D9>0.8,"⚡ WARNING","✓ OK")) -> ✓ OK | F9: =IF(D9>1,"REDUCE IMMEDIATELY",IF(D9>0.8,"Monitor closely",""))
A10: Max Correlated Positions | B10: 5 | C10: =MAX(Correlations!C4:C13) -> 1 | D10: =IF(B10>0,C10/B10,0) -> 0.2 | E10: =IF(D10>1,"⚠ BREACH",IF(D10>0.8,"⚡ WARNING","✓ OK")) -> ✓ OK | F10: =IF(D10>1,"REDUCE IMMEDIATELY",IF(D10>0.8,"Monitor closely",""))
A11: Max Days-Weighted Exposure | B11: 0.5 | C11: =SUMPRODUCT(Positions!K3:K102,1/(Positions!I3:I102-TODAY()+1))/Dashboard!B5 -> 2.0710059e-05 | D11: =IF(B11>0,C11/B11,0) -> 4.1420118e-05 | E11: =IF(D11>1,"⚠ BREACH",IF(D11>0.8,"⚡ WARNING","✓ OK")) -> ✓ OK | F11: =IF(D11>1,"REDUCE IMMEDIATELY",IF(D11>0.8,"Monitor closely",""))
A14: DRAWDOWN LIMITS
A15: Drawdown Level | B15: Threshold | C15: Action | D15: Current DD | E15: Triggered?
A16: Level 1 - Caution | B16: 0.05 | C16: Reduce Kelly fraction to 0.20 | D16: =Dashboard!B11 -> 0.0049751244 | E16: =IF(D16>=B16,"YES","NO") -> NO
A17: Level 2 - Warning | B17: 0.1 | C17: Reduce Kelly fraction to 0.15, no new positions | D17: =Dashboard!B11 -> 0.0049751244 | E17: =IF(D17>=B17,"YES","NO") -> NO
A18: Level 3 - Critical | B18: 0.15 | C18: Close 50% of positions, Kelly to 0.10 | D18: =Dashboard!B11 -> 0.0049751244 | E18: =IF(D18>=B18,"YES","NO") -> NO
A19: Level 4 - Stop | B19: 0.2 | C19: Close all positions, pause trading | D19: =Dashboard!B11 -> 0.0049751244 | E19: =IF(D19>=B19,"YES","NO") -> NO
A22: PER-TRADE LOSS MONITORING
A23: Positions with > 50% loss (consider closing):
A24: =SUMPRODUCT((Positions!N3:N102<-0.5)*1) -> 0
A25: Positions with edge gone (current edge < 2%):
A26: =SUMPRODUCT((ABS(Positions!F3:F102)<0.02)*(Positions!K3:K102>0)*1) -> 0

Sheet Stress Tests
A1: STRESS TESTING & SCENARIO ANALYSIS
A3: SCENARIO DEFINITIONS
A4: Scenario | B4: Description | C4: US Politics | D4: Crypto | E4: Fed/Macro | F4: Tech | G4: Sports | H4: Probability
A5: Base Case | B5: No major shocks | C5: 0 | D5: 0 | E5: 0 | F5: 0 | G5: 0 | H5: 0.6
A6: Political Shock | B6: Major political event, all political bets move against | C6: -0.2 | D6: -0.05 | E6: -0.1 | F6: 0 | G6: 0 | H6: 0.1
A7: Crypto Crash | B7: Crypto winter, regulatory crackdown | C7: 0 | D7: -0.4 | E7: -0.05 | F7: -0.1 | G7: 0 | H7: 0.08
A8: Fed Surprise | B8: Unexpected Fed action | C8: -0.05 | D8: -0.15 | E8: -0.25 | F8: -0.1 | G8: 0 | H8: 0.07
A9: Black Swan | B9: Major unexpected event | C9: -0.15 | D9: -0.2 | E9: -0.15 | F9: -0.15 | G9: -0.05 | H9: 0.05
A10: All Wrong | B10: Every position moves against you | C10: -0.3 | D10: -0.3 | E10: -0.3 | F10: -0.3 | G10: -0.3 | H10: 0.02
A11: Recovery Rally | B11: Positive sentiment across markets | C11: 0.1 | D11: 0.15 | E11: 0.05 | F11: 0.1 | G11: 0 | H11: 0.08
A14: SCENARIO P&L IMPACT
A15: Scenario | B15: Portfolio P&L ($) | C15: P&L % | D15: Worst Position | E15: Survives?
A16: =A5 -> Base Case | B16: =Correlations!$D$4*C5+Correlations!$D$5*D5+Correlations!$D$6*E5+Correlations!$D$7*F5+Correlations!$D$8*G5 -> 0 | C16: =IF(Dashboard!$B$5>0,B16/Dashboard!$B$5,0) -> 0 | E16: =IF(ABS(C16)<0.2,"✓ YES","⚠ NO") -> ✓ YES
A17: =A6 -> Political Shock | B17: =Correlations!$D$4*C6+Correlations!$D$5*D6+Correlations!$D$6*E6+Correlations!$D$7*F6+Correlations!$D$8*G6 -> -42 | C17: =IF(Dashboard!$B$5>0,B17/Dashboard!$B$5,0) -> -0.0042 | E17: =IF(ABS(C17)<0.2,"✓ YES","⚠ NO") -> ✓ YES
A18: =A7 -> Crypto Crash | B18: =Correlations!$D$4*C7+Correlations!$D$5*D7+Correlations!$D$6*E7+Correlations!$D$7*F7+Correlations!$D$8*G7 -> 0 | C18: =IF(Dashboard!$B$5>0,B18/Dashboard!$B$5,0) -> 0 | E18: =IF(ABS(C18)<0.2,"✓ YES","⚠ NO") -> ✓ YES
A19: =A8 -> Fed Surprise | B19: =Correlations!$D$4*C8+Correlations!$D$5*D8+Correlations!$D$6*E8+Correlations!$D$7*F8+Correlations!$D$8*G8 -> -10.5 | C19: =IF(Dashboard!$B$5>0,B19/Dashboard!$B$5,0) -> -0.00105 | E19: =IF(ABS(C19)<0.2,"✓ YES","⚠ NO") -> ✓ YES
A20: =A9 -> Black Swan | B20: =Correlations!$D$4*C9+Correlations!$D$5*D9+Correlations!$D$6*E9+Correlations!$D$7*F9+Correlations!$D$8*G9 -> -31.5 | C20: =IF(Dashboard!$B$5>0,B20/Dashboard!$B$5,0) -> -0.00315 | E20: =IF(ABS(C20)<0.2,"✓ YES","⚠ NO") -> ✓ YES
A21: =A10 -> All Wrong | B21: =Correlations!$D$4*C10+Correlations!$D$5*D10+Correlations!$D$6*E10+Correlations!$D$7*F10+Correlations!$D$8*G10 -> -63 | C21: =IF(Dashboard!$B$5>0,B21/Dashboard!$B$5,0) -> -0.0063 | E21: =IF(ABS(C21)<0.2,"✓ YES","⚠ NO") -> ✓ YES
A22: =A11 -> Recovery Rally | B22: =Correlations!$D$4*C11+Correlations!$D$5*D11+Correlations!$D$6*E11+Correlations!$D$7*F11+Correlations!$D$8*G11 -> 21 | C22: =IF(Dashboard!$B$5>0,B22/Dashboard!$B$5,0) -> 0.0021 | E22: =IF(ABS(C22)<0.2,"✓ YES","⚠ NO") -> ✓ YES
A24: EXPECTED LOSS (probability-weighted)
A25: =SUMPRODUCT(B16:B22,H5:H11) -> -6.09 | B25: =A25/Dashboard!B5 -> -0.000609
A26: Value at Risk (95%)
A27: =PERCENTILE(B16:B22,0.05) -> -56.7
A30: REVERSE STRESS TEST
A31: What shock causes 20% drawdown?
A32: Required uniform shock: | B32: =IF(Dashboard!B6>0,-0.2*Dashboard!B5/Dashboard!B6,0) -> -9.5238095

Sheet Checklist
A1: TRADE DECISION CHECKLIST
A3: Complete before entering ANY new position
A5: PRE-TRADE CHECKLIST
A6: Check | B6: Question | C6: Answer | D6: Pass?
A7: Edge Verification | B7: Is my edge > 5%? | D7: =IF(C7="Yes","✓","✗") -> ✗
A8: Edge Source | B8: What is my information advantage?
A9: Base Rate | B9: Have I considered base rates? | D9: =IF(C9="Yes","✓","✗") -> ✗
A10: Overconfidence | B10: Am I adjusting for overconfidence? | D10: =IF(C10="Yes","✓","✗") -> ✗
A11: Resolution Risk | B11: Are resolution criteria clear? | D11: =IF(C11="Yes","✓","✗") -> ✗
A12: Liquidity | B12: Can I exit if needed? (spread < 3%) | D12: =IF(C12="Yes","✓","✗") -> ✗
A13: Correlation | B13: Does this add to existing cluster exposure?
A14: Position Size | B14: Is suggested size within limits? | D14: =IF(C14="Yes","✓","✗") -> ✗
A15: Drawdown State | B15: Am I in a drawdown? Reduced sizing?
A16: News Catalyst | B16: Any imminent news that could move this?
A17: Time Horizon | B17: Does resolution timeline fit my strategy? | D17: =IF(C17="Yes","✓","✗") -> ✗
A18: Opportunity Cost | B18: Is capital better deployed elsewhere?
A20: CHECKLIST SUMMARY
A21: Checks Passed: | B21: =COUNTIF(D7:D18,"✓") -> 0
A22: Checks Failed: | B22: =COUNTIF(D7:D18,"✗") -> 7
A23: GO/NO-GO: | B23: =IF(B22>0,"⚠ NO-GO - Review failed checks","✓ PROCEED") -> ⚠ NO-GO - Review failed checks
A26: EXIT DECISION CHECKLIST
A27: Check | B27: Question | C27: Answer
A28: Edge Gone | B28: Has my edge closed (current < 2%)?
A29: Target Hit | B29: Has price reached my target?
A30: Stop Loss | B30: Has position lost > 50%?
A31: New Info | B31: Has new information changed my thesis?
A32: Better Opportunity | B32: Is capital needed for better opportunity?
A33: Resolution Near | B33: Is resolution < 7 days and no edge?

Sheet Rebalancing
A1: REBALANCING TRIGGERS
A3: AUTOMATIC TRIGGERS
A4: Trigger | B4: Condition | C4: Threshold | D4: Current | E4: Triggered? | F4: Action
A5: Position Drift | B5: Any position > 15% of portfolio | C5: 0.15 | D5: =IFERROR(MAX(Positions!L3:L102),0) -> 0.021 | E5: =IF(D5>C5,"⚠ YES","NO") -> NO | F5: Trim to 10%
A6: Cluster Concentration | B6: Any cluster > 30% of portfolio | C6: 0.3 | D6: =IFERROR(MAX(Correlations!E4:E13),0) -> 0.021 | E6: =IF(D6>C6,"⚠ YES","NO") -> NO | F6: Reduce cluster exposure
A7: Edge Decay | B7: Position edge < 50% of entry | C7: 0.5 | D7: =IFERROR(minifs(Positions!F3:F102,Positions!E3:E102,">0")/minifs(Positions!E3:E102,Positions!E3:E102,">0"),1) -> 1 | E7: =IF(D7>C7,"⚠ YES","NO") -> ⚠ YES | F7: Review & consider exit
A8: Resolution Approaching | B8: Position < 7 days to resolution | C8: 7 | D8: =IFERROR(MIN(Positions!I3:I102)-TODAY(),999) -> 1013 | E8: =IF(D8>C8,"⚠ YES","NO") -> ⚠ YES | F8: Exit or roll
A9: Drawdown Breach | B9: Portfolio drawdown > 10% | C9: 0.1 | D9: =Dashboard!B11 -> 0.0049751244 | E9: =IF(D9>C9,"⚠ YES","NO") -> NO | F9: Reduce all positions
A10: Cash Depleted | B10: Cash reserve < 5% | C10: 0.05 | D10: =IFERROR(Dashboard!B7/Dashboard!B5,1) -> 0.979 | E10: =IF(D10>C10,"⚠ YES","NO") -> ⚠ YES | F10: Close weakest positions
A11: Correlation Spike | B11: New correlated position added | E11: Manual | F11: Reduce overlapping exposure
A14: SCHEDULED REVIEWS
A15: Review Type | B15: Frequency | C15: Last Review | D15: Next Review | E15: Due?
A16: Position Review | B16: Daily | C16: 45677 | D16: =C16+1 -> 45678 | E16: =IF(D16<=TODAY(),"⚠ DUE","") -> ⚠ DUE
A17: Cluster Balance | B17: Weekly | C17: 45672 | D17: =C17+7 -> 45679 | E17: =IF(D17<=TODAY(),"⚠ DUE","") -> ⚠ DUE
A18: Full Portfolio Review | B18: Monthly | C18: 45658 | D18: =EOMONTH(C18,0)+1 -> 45689 | E18: =IF(D18<=TODAY(),"⚠ DUE","") -> ⚠ DUE
A19: Strategy Review | B19: Quarterly | C19: 45566 | D19: =EOMONTH(C19,2)+1 -> 45658 | E19: =IF(D19<=TODAY(),"⚠ DUE","") -> ⚠ DUE
A22: REBALANCING LOG
A23: Date | B23: Trigger | C23: Position | D23: Action Taken | E23: Old Size | F23: New Size | G23: Notes

Sheet Attribution
A1: PERFORMANCE ATTRIBUTION
G2: =B6+B8 -> 10050 | J2: =IF(COUNTIF(H16:H1000,"Win")+COUNTIF(H16:H1000,"Loss")>0,COUNTIF(H16:H1000,"Win")/(COUNTIF(H16:H1000,"Win")+COUNTIF(H16:H1000,"Loss")),0) -> 1 | K2: =IF(COUNT(J16:J1000)>0,AVERAGE(J16:J1000),0) -> 0.15 | L2: =IF(COUNT(K16:K1000)>0,AVERAGE(K16:K1000),0) -> 0.16
A3: PORTFOLIO PERFORMANCE SUMMARY | D3: ATTRIBUTION BY CLUSTER
A4: Metric | B4: Value | D4: Cluster | E4: Trades | F4: P&L | G4: Win Rate | H4: Avg Brier
A5: Total Trades | B5: =COUNTA(A16:A1000) -> 1 | D5: US Politics | E5: =COUNTIF(G16:G1000,D5) -> 1 | F5: =SUMIF(G16:G1000,D5,I16:I1000) -> 50 | G5: =IFERROR(COUNTIFS(G16:G1000,D5,H16:H1000,"Win")/(COUNTIFS(G16:G1000,D5,H16:H1000,"Win")+COUNTIFS(G16:G1000,D5,H16:H1000,"Loss")),0) -> 1 | H5: =IFERROR(AVERAGEIF(G16:G1000,D5,K16:K1000),0) -> 0.16
A6: Starting Bankroll | B6: 10000 | D6: Crypto | E6: =COUNTIF(G16:G1000,D6) -> 0 | F6: =SUMIF(G16:G1000,D6,I16:I1000) -> 0 | G6: =IFERROR(COUNTIFS(G16:G1000,D6,H16:H1000,"Win")/(COUNTIFS(G16:G1000,D6,H16:H1000,"Win")+COUNTIFS(G16:G1000,D6,H16:H1000,"Loss")),0) -> 0 | H6: =IFERROR(AVERAGEIF(G16:G1000,D6,K16:K1000),0) -> 0
A7: Current Bankroll | B7: =G2 -> 10050 | D7: Fed/Macro | E7: =COUNTIF(G16:G1000,D7) -> 0 | F7: =SUMIF(G16:G1000,D7,I16:I1000) -> 0 | G7: =IFERROR(COUNTIFS(G16:G1000,D7,H16:H1000,"Win")/(COUNTIFS(G16:G1000,D7,H16:H1000,"Win")+COUNTIFS(G16:G1000,D7,H16:H1000,"Loss")),0) -> 0 | H7: =IFERROR(AVERAGEIF(G16:G1000,D7,K16:K1000),0) -> 0
A8: Total P&L | B8: =SUM(I16:I1000) -> 50 | D8: Tech | E8: =COUNTIF(G16:G1000,D8) -> 0 | F8: =SUMIF(G16:G1000,D8,I16:I1000) -> 0 | G8: =IFERROR(COUNTIFS(G16:G1000,D8,H16:H1000,"Win")/(COUNTIFS(G16:G1000,D8,H16:H1000,"Win")+COUNTIFS(G16:G1000,D8,H16:H1000,"Loss")),0) -> 0 | H8: =IFERROR(AVERAGEIF(G16:G1000,D8,K16:K1000),0) -> 0
A9: Total Return % | B9: =IF(B6>0,B8/B6,0) -> 0.005 | D9: Sports | E9: =COUNTIF(G16:G1000,D9) -> 0 | F9: =SUMIF(G16:G1000,D9,I16:I1000) -> 0 | G9: =IFERROR(COUNTIFS(G16:G1000,D9,H16:H1000,"Win")/(COUNTIFS(G16:G1000,D9,H16:H1000,"Win")+COUNTIFS(G16:G1000,D9,H16:H1000,"Loss")),0) -> 0 | H9: =IFERROR(AVERAGEIF(G16:G1000,D9,K16:K1000),0) -> 0
A10: Win Rate | B10: =J2 -> 1 | D10: Entertainment | E10: =COUNTIF(G16:G1000,D10) -> 0 | F10: =SUMIF(G16:G1000,D10,I16:I1000) -> 0 | G10: =IFERROR(COUNTIFS(G16:G1000,D10,H16:H1000,"Win")/(COUNTIFS(G16:G1000,D10,H16:H1000,"Win")+COUNTIFS(G16:G1000,D10,H16:H1000,"Loss")),0) -> 0 | H10: =IFERROR(AVERAGEIF(G16:G1000,D10,K16:K1000),0) -> 0
A11: Avg Edge Captured | B11: =K2 -> 0.15 | D11: Other | E11: =COUNTIF(G16:G1000,D11) -> 0 | F11: =SUMIF(G16:G1000,D11,I16:I1000) -> 0 | G11: =IFERROR(COUNTIFS(G16:G1000,D11,H16:H1000,"Win")/(COUNTIFS(G16:G1000,D11,H16:H1000,"Win")+COUNTIFS(G16:G1000,D11,H16:H1000,"Loss")),0) -> 0 | H11: =IFERROR(AVERAGEIF(G16:G1000,D11,K16:K1000),0) -> 0
A12: Portfolio Brier Score | B12: =L2 -> 0.16
A14: TRADE LOG
A15: Trade ID | B15: Market | C15: Direction | D15: Entry Date | E15: Exit Date | F15: Entry Price | G15: Cluster | H15: Outcome | I15: P&L ($) | J15: Edge Captured | K15: Brier Score | L15: Your Prob | M15: Actual | N15: Notes
A16: 1 | B16: Sample Market | C16: YES | D16: 45658 | E16: 45672 | F16: 0.45 | G16: US Politics | H16: Win | I16: 50 | J16: =IF(H16="Win",L16-F16,F16-L16) -> 0.15 | K16: =(L16-M16)^2 -> 0.16 | L16: 0.6 | M16: 1

Sheet Instructions
A1: POLYMARKET PORTFOLIO MANAGEMENT - INSTRUCTIONS
A3: HOW TO USE THIS WORKBOOK
A5: 1. DASHBOARD (Start Here)
A6: - Set your total bankroll in cell B5 (blue = input)
A7: - Monitor all key metrics and alerts
A8: - Use the Quick Sizing Calculator for new positions
A10: 2. POSITIONS
A11: - Enter all active positions here
A12: - Blue cells are inputs, black cells are calculated
A13: - Update current prices regularly
A14: - Formulas auto-calculate P&L, Greeks, etc.
A16: 3. SIZING
... A74: 4. Monthly: Full Attribution review, strategy adjustment
